{
  "id": "education",
  "title": "Образование, курсы, репетиторы",
  "match": [
    "курс", "школа", "обучен", "репетит", "академ", "тренинг",
    "семинар", "коуч", "образован", "вуз", "детск", "развив"
  ],
  "synonyms": [
    "курсы",
    "обучение",
    "школа",
    "репетитор",
    "тренинг"
  ],
  "targets": [
    "английский",
    "математика",
    "программирование",
    "дизайн",
    "для детей",
    "для взрослых",
    "с нуля",
    "подготовка к ЕГЭ"
  ],
  "vertical_minus_words": [
    "бесплатно",
    "торрент",
    "скачать",
    "википедия",
    "вакансии",
    "работа",
    "pikabu",
    "youtube"
  ],
  "modifiers_per_city": [
    "запись",
    "цена",
    "отзывы",
    "офлайн",
    "очно"
  ],
  "modifiers_global": [
    "онлайн",
    "программа",
    "длительность",
    "сертификат"
  ]
}
